poly_mcp_server/__init__.py
poly_mcp_server/server.py
poly_mcp_server-0.2.3.dist-info/METADATA
poly_mcp_server-0.2.3.dist-info/WHEEL
poly_mcp_server-0.2.3.dist-info/entry_points.txt
poly_mcp_server-0.2.3.dist-info/RECORD
