Metadata-Version: 2.4
Name: poly-mcp-server
Version: 0.2.3
Summary: Poly MCP Server - Wordit Edutem database reporting tool
Project-URL: Homepage, https://github.com/yourusername/poly-mcp-server
Project-URL: Repository, https://github.com/yourusername/poly-mcp-server
Project-URL: Issues, https://github.com/yourusername/poly-mcp-server/issues
Author-email: Poly MCP <poly-mcp@example.com>
License: MIT
Keywords: ai,mcp,model-context-protocol,tools
Classifier: Development Status :: 4 - Beta
Classifier: Intended Audience :: Developers
Classifier: License :: OSI Approved :: MIT License
Classifier: Programming Language :: Python :: 3
Classifier: Programming Language :: Python :: 3.10
Classifier: Programming Language :: Python :: 3.11
Classifier: Programming Language :: Python :: 3.12
Requires-Python: >=3.10
Requires-Dist: mcp>=0.9.0
Requires-Dist: openpyxl>=3.1.0
Requires-Dist: psycopg2-binary>=2.9.0
Requires-Dist: python-dateutil>=2.8.0
Provides-Extra: dev
Requires-Dist: pytest-asyncio>=0.21.0; extra == 'dev'
Requires-Dist: pytest>=7.0.0; extra == 'dev'
